fieldfitter/__init__.py
fieldfitter/fitter.py
fieldfitter-0.6.0.dist-info/licenses/LICENSE
fieldfitter-0.6.0.dist-info/METADATA
fieldfitter-0.6.0.dist-info/WHEEL
fieldfitter-0.6.0.dist-info/top_level.txt
fieldfitter-0.6.0.dist-info/RECORD
