Metadata-Version: 2.4
Name: fieldfitter
Version: 0.6.0
Summary: Scaffold/model field fitting library using Zinc.
Author-email: Richard Christie <r.christie@auckland.ac.nz>
License-Expression: Apache-2.0
Keywords: Medical,Physiology,Anatomical,Mesh,Finite Element,Fitting,SPARC
Classifier: Programming Language :: Python :: 3
Classifier: Operating System :: OS Independent
Classifier: Topic :: Scientific/Engineering :: Medical Science Apps.
Requires-Python: >=3.8
License-File: LICENSE
Requires-Dist: cmlibs.utils>=0.12.0
Requires-Dist: cmlibs.zinc>=4.1
Dynamic: license-file
